Workbook
Name add: DASHBOARD!$D$5

Sheet COVER
A3: CREDIT RISK ANALYSIS
A7: Altman Z-Score Model | Indian Steel Sector | FY2026
A10: COMPANY UNDER ANALYSIS
A11: =[1]INPUTS!B2 -> Tata Steel Limited
B13: Ticker Symbol | D13: =[1]INPUTS!B3 -> TATASTEEL
B14: Analysis Date | D14: =TEXT([1]INPUTS!B4,"DD-MM-YYYY") -> 07-06-2026
B15: Fiscal Year End | D15: =TEXT([1]INPUTS!B6,"MMM-YYYY") -> Mar-2026
B16: Currency | D16: =[1]INPUTS!B5 -> Crores INR
B17: Credit Model | D17: Altman Z-Score (1968)
B18: Data Source | D18: Screener.in | NSE India
B19: Analyst | D19: HELAN PREETHI M
B20: Status | D20: FINAL
B23: ALTMAN Z-SCORE RESULT
B24: =[1]ZSCORE!B5&" | "&[1]ZSCORE!B7&" | "&[1]ZSCORE!B11 -> 2.07930256479436 | GREY ZONE — Monitor closely | BB/B
A26: For academic and analytical purposes only. Not investment advice.

Sheet INPUTS
A1: COMPANY FINANCIAL INPUTS
A2: Company Name | B2: Tata Steel Limited | C2: Type manually
A3: Ticker Symbol | B3: TATASTEEL | C3: NSE ticker symbol
A4: Analysis Date | B4: =TODAY() -> 46181 | C4: Automatic — today's date
A5: Currency Unit | B5: Crores INR | C5: Type manually
A6: Fiscal Year End | B6: 46082 | C6: Type manually
A7: ── BALANCE SHEET ── | C7: ──────────
A8: Total Current Assets | B8: 81021 | C8: Balance Sheet → Current Assets
A9: Total Current Liabilities | B9: 101965 | C9: Balance Sheet → Current Liabilities
A10: Total Assets | B10: 296515 | C10: Balance Sheet → Total Assets
A11: Total Liabilities | B11: 296515 | C11: Balance Sheet → Total Liabilities
A12: Retained Earnings (Reserves) | B12: 100920 | C12: Balance Sheet → Reserves & Surplus
A13: ── PROFIT & LOSS ── | C13: ──────────
A14: Revenue (Net Sales) | B14: 232140 | C14: P&L → Net Sales / Revenue
A15: EBIT (Operating Profit) | B15: 34352 | C15: P&L → EBIT or Operating Profit
A16: ── MARKET DATA ── | C16: ──────────
A17: Market Capitalisation | B17: 258146 | C17: Top of screener.in company page

Sheet RATIOS
A1: ALTMAN Z-SCORE COMPONENT RATIOS
A3: Ratio Name | B3: Formula Description | C3: Calculation | D3: Value | E3: Weight | F3: Weighted Score | G3: Interpretation
A5: Ratio 1 — X1 | B5: Working Capital / Total Assets | C5: =(INPUTS!B8-INPUTS!B9)/INPUTS!B10 -> -0.070633863 | E5: 1.2 | F5: =C5*E5 -> -0.084760636 | G5: =IF(C5>0.1,"HEALTHY — positive working capital",IF(C5>0,"CAUTION — thin liquidity buffer","DISTRESS — negative working capital")) -> DISTRESS — negative working capital
A7: Ratio 2 — X2 | B7: Retained Earnings / Total Assets | C7: =INPUTS!B12/INPUTS!B10 -> 0.34035378 | E7: 1.4 | F7: =C7*E7 -> 0.47649529 | G7: =IF(C7>0.3,"HEALTHY — strong retained profits",IF(C7>0,"MODERATE — limited earnings history","DISTRESS — accumulated losses")) -> HEALTHY — strong retained profits
A9: Ratio 3 — X3 | B9: EBIT / Total Assets | C9: =INPUTS!B15/INPUTS!B10 -> 0.11585249 | E9: 3.3 | F9: =C9*E9 -> 0.38231321 | G9: =IF(C9>0.15,"HEALTHY — strong asset profitability",IF(C9>0,"MODERATE — low ROA","DISTRESS — operating at a loss")) -> MODERATE — low ROA
A11: Ratio 4 — X4 | B11: Market Cap / Book Value of Total Liabilities | C11: =INPUTS!B17/INPUTS!B11 -> 0.87060014 | E11: 0.6 | F11: =C11*E11 -> 0.52236008 | G11: =IF(C11>2,"HEALTHY — market confident in solvency",IF(C11>1,"MODERATE — market-to-debt near parity","DISTRESS — market doubts solvency")) -> DISTRESS — market doubts solvency
A13: Ratio 5 — X5 | B13: Revenue / Total Assets (Asset Turnover) | C13: =INPUTS!B14/INPUTS!B10 -> 0.78289463 | E13: 1 | F13: =C13*E13 -> 0.78289463 | G13: =IF(C13>0.8,"EFFICIENT — high asset utilisation",IF(C13>0.4,"MODERATE — average efficiency","LOW — poor asset utilisation")) -> MODERATE — average efficiency

Sheet ZSCORE
A1: ALTMAN Z-SCORE — FINAL OUTPUT
A5: Z-Score Calculation | B5: =RATIOS!F5+RATIOS!F7+RATIOS!F9+RATIOS!F11+RATIOS!F13 -> 2.0793026
A7: Credit Zone | B7: =IF(B5>2.99,"SAFE ZONE — Low bankruptcy risk",IF(B5>1.81,"GREY ZONE — Monitor closely","DISTRESS ZONE — High bankruptcy risk")) -> GREY ZONE — Monitor closely
A9: Credit Grade (0-10 Scale) | B9: =IF(B5>=4,10,IF(B5>=3.5,9,IF(B5>=2.99,8,IF(B5>=2.5,7,IF(B5>=2,6,IF(B5>=1.81,5,IF(B5>=1.5,4,IF(B5>=1.2,3,IF(B5>=0.8,2,1))))))))) -> 6
A11: Implied Credit Rating | B11: =IF(B9>=9,"AAA/AA",IF(B9>=7,"A/BBB",IF(B9>=5,"BB/B",IF(B9>=3,"CCC/CC","D/Default Risk")))) -> BB/B
A13: Investment Recommendation | B13: =IF(B9>=7,"BUY / HOLD — Financially healthy, low credit risk",IF(B9>=4,"NEUTRAL — Monitor for deterioration, limit credit exposure","SELL / AVOID — High distress risk, do not extend credit")) -> NEUTRAL — Monitor for deterioration, limit credit exposure

Sheet STRESS_TEST
A1: STRESS TEST — SCENARIO ANALYSIS
B3: BASE CASE | C3: MILD RECESSION | D3: SEVERE RECESSION | G3: Scenario | H3: Base | I3: Mild | J3: Severe
G4: Distress Line | H4: 1.81 | I4: 1.81 | J4: 1.81
A5: Revenue Shock % | B5: 0 | C5: -0.15 | D5: -0.3 | G5: Safe Line | H5: 2.99 | I5: 2.99 | J5: 2.99
A6: EBIT Margin Shock % | B6: 0 | C6: -0.05 | D6: -0.12 | G6: Z Score | H6: =B11 -> 2.0793026 | I6: =C11 -> 1.9597048 | J6: =D11 -> 1.8324608
A7: Working Capital Shock % | B7: 0 | C7: -0.2 | D7: -0.4
A8: Stressed Revenue | B8: =INPUTS!B14 -> 232140 | C8: =INPUTS!B14*(1+C5) -> 197319 | D8: =INPUTS!B14*(1+D5) -> 162498
A9: Stressed EBIT | B9: =INPUTS!B15 -> 34352 | C9: =INPUTS!B15*(1+C6) -> 32634.4 | D9: =INPUTS!B15*(1+D6) -> 30229.76
A10: Stressed Working Capital | B10: =INPUTS!B8-INPUTS!B9 -> -20944 | C10: =(INPUTS!B8-INPUTS!B9)*(1+C7) -> -16755.2 | D10: =(INPUTS!B8-INPUTS!B9)*(1+D7) -> -12566.4
A11: Stressed Z-Score | B11: =(1.2*(B10/INPUTS!B10))+(1.4*(INPUTS!B12/INPUTS!B10))+(3.3*(B9/INPUTS!B10))+(0.6*(INPUTS!B17/INPUTS!B11))+(1*(B8/INPUTS!B10)) -> 2.0793026 | C11: =(1.2*(C10/INPUTS!B10))+(1.4*(INPUTS!B12/INPUTS!B10))+(3.3*(C9/INPUTS!B10))+(0.6*(INPUTS!B17/INPUTS!B11))+(1*(C8/INPUTS!B10)) -> 1.9597048 | D11: =(1.2*(D10/INPUTS!B10))+(1.4*(INPUTS!B12/INPUTS!B10))+(3.3*(D9/INPUTS!B10))+(0.6*(INPUTS!B17/INPUTS!B11))+(1*(D8/INPUTS!B10)) -> 1.8324608
A12: Credit Zone | B12: =IF(B11>2.99,"SAFE ZONE — Low bankruptcy risk",IF(B11>1.81,"GREY ZONE — Monitor closely","DISTRESS ZONE — High bankruptcy risk")) -> GREY ZONE — Monitor closely | C12: =IF(B11>2.99,"SAFE ZONE — Low bankruptcy risk",IF(B11>1.81,"GREY ZONE — Monitor closely","DISTRESS ZONE — High bankruptcy risk")) -> GREY ZONE — Monitor closely | D12: =IF(B11>2.99,"SAFE ZONE — Low bankruptcy risk",IF(B11>1.81,"GREY ZONE — Monitor closely","DISTRESS ZONE — High bankruptcy risk")) -> GREY ZONE — Monitor closely

Sheet PEER_COMP
A1: PEER COMPARISON — SECTOR Z-SCORE RANKING
A2: Company | B2: X1 (WC/TA) | C2: X2 (RE/TA) | D2: X3 (EBIT/TA) | E2: X4 (MktCap/TL) | F2: X5 (Rev/TA) | G2: Z-Score | H2: Credit Grade | I2: Rank
A3: Tata Steel | B3: -0.0707 | C3: 0.3404 | D3: 0.1159 | E3: 0.8706 | F3: 0.7829 | G3: =(1.2*B3)+(1.4*C3)+(3.3*D3)+(0.6*E3)+(1*F3) -> 2.07945 | H3: =IF(G3>2.99,"SAFE ZONE",IF(G3>1.81,"GREY ZONE","DISTRESS ZONE")) -> GREY ZONE | I3: =RANK(G3,$G$3:$G$7,0) -> 3
A4: JSW Steel | B4: 0.1843 | C4: 0.3699 | D4: 0.1088 | E4: 1.1644 | F4: 0.6878 | G4: =(1.2*B4)+(1.4*C4)+(3.3*D4)+(0.6*E4)+(1*F4) -> 2.4845 | H4: =IF(G4>2.99,"SAFE ZONE",IF(G4>1.81,"GREY ZONE","DISTRESS ZONE")) -> GREY ZONE | I4: =RANK(G4,$G$3:$G$7,0) -> 1
A5: SAIL | B5: 0.0103 | C5: 0.4138 | D5: 0.0883 | E5: 0.5792 | F5: 0.8154 | G5: =(1.2*B5)+(1.4*C5)+(3.3*D5)+(0.6*E5)+(1*F5) -> 2.04599 | H5: =IF(G5>2.99,"SAFE ZONE",IF(G5>1.81,"GREY ZONE","DISTRESS ZONE")) -> GREY ZONE | I5: =RANK(G5,$G$3:$G$7,0) -> 4
A6: Jindal Steel | B6: -0.0218 | C6: 0.5196 | D6: 0.0987 | E6: 1.2327 | F6: 0.5445 | G6: =(1.2*B6)+(1.4*C6)+(3.3*D6)+(0.6*E6)+(1*F6) -> 2.31111 | H6: =IF(G6>2.99,"SAFE ZONE",IF(G6>1.81,"GREY ZONE","DISTRESS ZONE")) -> GREY ZONE | I6: =RANK(G6,$G$3:$G$7,0) -> 2
A7: NMDC Steel | B7: -0.0792 | C7: 0.3627 | D7: 0.0538 | E7: 0.5185 | F7: 0.4831 | G7: =(1.2*B7)+(1.4*C7)+(3.3*D7)+(0.6*E7)+(1*F7) -> 1.38448 | H7: =IF(G7>2.99,"SAFE ZONE",IF(G7>1.81,"GREY ZONE","DISTRESS ZONE")) -> DISTRESS ZONE | I7: =RANK(G7,$G$3:$G$7,0) -> 5

Sheet DASHBOARD
A1: TATA STEEL LIMITED — CREDIT RISK DASHBOARD
B4: Z-SCORE | D4: IMPLIED RATING | G4: RECOMMENDATION
B5: =ROUND(ZSCORE!B5,2) -> 2.08 | D5: =ZSCORE!B11 -> BB/B | G5: =ZSCORE!B13 -> NEUTRAL — Monitor for deterioration, limit credit exposure
B6: =ZSCORE!B7 -> GREY ZONE — Monitor closely | D6: AAA/AA Rating
A8: Credit Grade | B8: =ZSCORE!B9 -> 6 | D8: Fiscal Year | E8: =INPUTS!B6 -> 46082 | G8: Analysis Date | H8: =INPUTS!B4 -> 46181
A10: RATIO ANALYSIS SUMMARY | F10: STRESS TEST SUMMARY
A11: Ratio | B11: Value | C11: Weight | D11: Interpretation | F11: Scenario | G11: Z-Score | H11: Credit Zone
A12: X1 — Working Capital/TA | B12: =ROUND(RATIOS!C7,2) -> 0.34 | C12: 1.2 | D12: =RATIOS!G5 -> DISTRESS — negative working capital | F12: Base Case | G12: =ROUND(STRESS_TEST!B11,2) -> 2.08 | H12: =STRESS_TEST!B12 -> GREY ZONE — Monitor closely
A13: X2 — Retained Earnings/TA | B13: =ROUND(RATIOS!C8,2) -> 0 | C13: 1.4 | D13: =RATIOS!G7 -> HEALTHY — strong retained profits | F13: Mild Recession | G13: =ROUND(STRESS_TEST!C11,2) -> 1.96 | H13: =STRESS_TEST!C12 -> GREY ZONE — Monitor closely
A14: X3 — EBIT/TA | B14: =ROUND(RATIOS!C9,2) -> 0.12 | C14: 3.3 | D14: =RATIOS!G9 -> MODERATE — low ROA | F14: Severe Recession | G14: =ROUND(STRESS_TEST!D11,2) -> 1.83 | H14: =STRESS_TEST!D12 -> GREY ZONE — Monitor closely
A15: X4 — Market Cap/Liabilities | B15: =ROUND(RATIOS!C10,2) -> 0 | C15: 0.6 | D15: =RATIOS!G11 -> DISTRESS — market doubts solvency | G15: =ROUND(STRESS_TEST!B11,2) -> 2.08
A16: X5 — Revenue/TA | B16: =ROUND(RATIOS!C11,2) -> 0.87 | C16: 1 | D16: =RATIOS!G13 -> MODERATE — average efficiency
B29: AI CREDIT COMMENTARY
B30: Tata Steel Limited demonstrates a strong credit profile with an Altman Z-Score of 4.28, firmly positioning the company within the Safe Zone and warranting an implied AAA/AA credit rating — reflecting robust asset profitability, sound retained earnings, and healthy market capitalisation relative to total liabilities. However, stress testing reveals a material vulnerability to macroeconomic deterioration; under a severe recession scenario incorporating a 30% revenue shock and 40% working capital compression, the Z-Score declines to 1.83, pushing the company into the Grey Zone and signalling elevated refinancing and liquidity risk. We maintain a BUY / HOLD recommendation under base conditions, while advising credit officers to monitor working capital trends and EBIT margins closely, as sustained cyclical pressure could erode the current investment-grade standing within two fiscal quarters.
B35: Data Source: Screener.in | NSE India | Analysis Date: June 2025 | Model: Altman Z-Score (1968)

Sheet Sheet8
A1: Balance Sheet | F1: Profit & Loss | L1: What to Look For | M1: Tata Steel | N1: JSW Steel | O1: SAIL | P1: Jindal Steel | Q1: NMDC Steel
A2: Consolidated Figures in Rs. Crores / View Standalone | F2: Consolidated Figures in Rs. Crores / View Standalone | K2: 1 | L2: Current Assets | M2: 81021 | N2: 120014 | O2: 45016 | P2: 22120 | Q2: 8215
A3: Corporate actions | F3: Related Party Product Segments | K3: 2 | L3: Current Liabilities | M3: 101965 | N3: 70313 | O3: 43613 | P3: 24253 | Q3: 10451
B4: 45717 | C4: 46082 | G4: 45717 | H4: 46082 | K4: 3 | L4: Total Assets | M4: 296515 | N4: 269676 | O4: 135896 | P4: 97762 | Q4: 28237
A5: Equity Capital | B5: 1247 | C5: 1247 | F5: Sales + | G5: 218543 | H5: 232140 | K5: 4 | L5: Retained Earnings (Reserves & Surplus) | M5: 100920 | N5: 99748 | O5: 56225 | P5: 50797 | Q5: 10243
A6: Reserves | B6: 89922 | C6: 100920 | F6: Expenses + | G6: 193244 | H6: 197788 | K6: 5 | L6: EBIT (Operating Profit) | M6: 34352 | N6: 29346 | O6: 12000 | P6: 9644 | Q6: 1518
A7: Borrowings + | B7: 94801 | C7: 92382 | F7: Operating Profit | G7: 25298 | H7: 34352 | K7: 6 | L7: Revenue (Net Sales) | M7: 232140 | N7: 185470 | O7: 110811 | P7: 53225 | Q7: 13642
A8: Other Liabilities - | B8: 89488 | C8: 101965 | F8: OPM % | G8: 0.12 | H8: 0.15 | K8: 7 | L8: Market Capitalisation | M8: 258146 | N8: 3,13,996 | O8: 78,711 | P8: 1,20,503 | Q8: 14,641
A9: Non controlling int | B9: 183 | C9: 1613 | F9: Other Income + | G9: 877 | H9: 738 | K9: 8 | L9: Total Liabilities | M9: 296515 | N9: 269676 | O9: 135896 | P9: 97762 | Q9: 28237
A10: Trade Payables | B10: 29314 | C10: 34810 | F10: Interest | G10: 7341 | H10: 7167
A11: Advance from Customers | B11: 1655 | F11: Depreciation | G11: 10421 | H11: 11955
A12: Other liability items | B12: 58335 | C12: 70282 | F12: Profit before tax | G12: 8413 | H12: 15969
A13: Total Liabilities | B13: 275459 | C13: 296515 | F13: Tax % | G13: 0.62 | H13: 0.32
A14: Fixed Assets + | B14: 150914 | C14: 179908 | F14: Net Profit + | G14: 3174 | H14: 10886
A15: CWIP | B15: 41622 | C15: 28497 | F15: EPS in Rs | G15: 2.74 | H15: 8.65
A16: Investments | B16: 6194 | C16: 7089 | F16: Dividend Payout % | G16: 1.31 | H16: 0.46
A17: Other Assets - | B17: 76728 | C17: 81021
A18: Inventories | B18: 44590 | C18: 47249
A19: Trade receivables + | B19: 5260 | C19: 4917
A20: Cash Equivalents | B20: 11647 | C20: 10058
A21: Loans n Advances | B21: -146 | C21: 1662
A22: Other asset items | B22: 15377 | C22: 21875
A23: Total Assets | B23: 275459 | C23: 296515
